sdq_mlb/__init__.py
sdq_mlb/df.py
sdq_mlb/player.py
sdq_mlb/players.py
sdq_mlb/types.py
sdq_mlb/utils.py
sdq_mlb/baseball_savant/__init__.py
sdq_mlb/baseball_savant/client.py
sdq_mlb/baseball_savant/types.py
sdq_mlb/db/__init__.py
sdq_mlb/db/client.py
sdq_mlb/db/player.py
sdq_mlb-0.0.1a25.dist-info/METADATA
sdq_mlb-0.0.1a25.dist-info/WHEEL
sdq_mlb-0.0.1a25.dist-info/RECORD
