Metadata-Version: 2.3
Name: sdq_mlb
Version: 0.0.1a25
Summary: Playground with multiple baseball websites
Author: Seb
Classifier: Environment :: Web Environment
Classifier: Intended Audience :: Developers
Classifier: Operating System :: OS Independent
Classifier: Programming Language :: Python
Classifier: Programming Language :: Python :: 3
Classifier: Programming Language :: Python :: 3 :: Only
Classifier: Programming Language :: Python :: 3.10
Classifier: Programming Language :: Python :: 3.11
Classifier: Programming Language :: Python :: 3.12
Requires-Python: >=3.10
Requires-Dist: beautifulsoup4
Requires-Dist: httpx
Requires-Dist: lxml
Requires-Dist: nbformat
Requires-Dist: pandas
Requires-Dist: plotly
Requires-Dist: polars
Requires-Dist: pyarrow
Provides-Extra: dev
Requires-Dist: black; extra == 'dev'
Requires-Dist: build; extra == 'dev'
Requires-Dist: flake8; extra == 'dev'
Requires-Dist: ipykernel; extra == 'dev'
Requires-Dist: mypy; extra == 'dev'
Requires-Dist: pytest; extra == 'dev'
Requires-Dist: pytest-asyncio; extra == 'dev'
Requires-Dist: pytest-cov; extra == 'dev'
Requires-Dist: pytest-mock; extra == 'dev'
Requires-Dist: pytest-xdist; extra == 'dev'
Requires-Dist: twine; extra == 'dev'
Requires-Dist: types-beautifulsoup4; extra == 'dev'
